{"data":{"site":{"siteMetadata":{"author":{"name":"Felipe Ventura","bio":"Building community networks","photo":"/photo.jpg","contacts":{"linkedin":"fvntr","github":"fvntr","twitter":"fvntr","email":"fvntra@gmail.com","soundcloud":"fvntr"}},"menu":[{"label":"Articles","path":"/"},{"label":"About me","path":"/pages/about"},{"label":"Contact me","path":"/pages/contacts"}],"url":"https://fvntr.github.io/fvntr.com/","title":"Felipe Ventura","subtitle":"Building community networks","copyright":"","disqusShortname":""}}}}